test/__init__.py
test/test_handlers.py
test/test_utils.py
test/protocols/__init__.py
test/protocols/test_BasicMessage.py
test/protocols/test_CommitedAnswer.py
test/protocols/test_Connecting.py
test/protocols/test_IssueCredential.py
test/protocols/test_IssuerSetup.py
test/protocols/test_PresentProof.py
test/protocols/test_Protocol.py
test/protocols/test_QuestionAnswer.py
test/protocols/test_UpdateConfigs.py
test/protocols/test_UpdateEndpoint.py
test/protocols/test_WriteCredentialDefinition.py
test/protocols/test_WriteSchema.py
test/protocols/v0_7/__init__.py
test/protocols/v0_7/test_Provision.py
test/protocols/v1_0/__init__.py
test/protocols/v1_0/test_IssueCredential.py
test/protocols/v1_0/test_OutOfBand.py
test/protocols/v1_0/test_Relationship.py
verity_sdk/__init__.py
verity_sdk/handlers.py
verity_sdk/transports.py
verity_sdk/version.py
verity_sdk/wallet.py
verity_sdk/protocols/BasicMessage.py
verity_sdk/protocols/CommittedAnswer.py
verity_sdk/protocols/IssuerSetup.py
verity_sdk/protocols/Protocol.py
verity_sdk/protocols/UpdateConfigs.py
verity_sdk/protocols/UpdateEndpoint.py
verity_sdk/protocols/WriteCredentialDefinition.py
verity_sdk/protocols/WriteSchema.py
verity_sdk/protocols/__init__.py
verity_sdk/protocols/v0_6/IssuerSetup.py
verity_sdk/protocols/v0_6/UpdateConfigs.py
verity_sdk/protocols/v0_6/UpdateEndpoint.py
verity_sdk/protocols/v0_6/WriteCredentialDefinition.py
verity_sdk/protocols/v0_6/WriteSchema.py
verity_sdk/protocols/v0_6/__init__.py
verity_sdk/protocols/v0_7/Provision.py
verity_sdk/protocols/v0_7/__init__.py
verity_sdk/protocols/v1_0/BasicMessage.py
verity_sdk/protocols/v1_0/CommittedAnswer.py
verity_sdk/protocols/v1_0/Connecting.py
verity_sdk/protocols/v1_0/IssueCredential.py
verity_sdk/protocols/v1_0/OutOfBand.py
verity_sdk/protocols/v1_0/PresentProof.py
verity_sdk/protocols/v1_0/QuestionAnswer.py
verity_sdk/protocols/v1_0/Relationship.py
verity_sdk/protocols/v1_0/__init__.py
verity_sdk-0.6.1.dist-info/DESCRIPTION.rst
verity_sdk-0.6.1.dist-info/METADATA
verity_sdk-0.6.1.dist-info/RECORD
verity_sdk-0.6.1.dist-info/WHEEL
verity_sdk-0.6.1.dist-info/metadata.json
verity_sdk-0.6.1.dist-info/top_level.txt
