Metadata-Version: 2.0
Name: verity-sdk
Version: 0.6.1
Summary: The official Python SDK for Evernym's Verity
Home-page: https://github.com/evernym/verity-sdk
Author: Evernym, Inc.
Author-email: dev@evernym.com
License: Apache-2.0
Platform: UNKNOWN
Requires-Python: ~=3.6
Requires-Dist: base58 (~=2.1.0)
Requires-Dist: requests (~=2.25.1)
Requires-Dist: vdr-tools (~=0.8.4)
